deltastream_sdk/__init__.py
deltastream_sdk/client.py
deltastream_sdk/exceptions.py
deltastream_sdk/models/__init__.py
deltastream_sdk/models/base.py
deltastream_sdk/models/changelogs.py
deltastream_sdk/models/compute_pools.py
deltastream_sdk/models/databases.py
deltastream_sdk/models/descriptor_sources.py
deltastream_sdk/models/entities.py
deltastream_sdk/models/function_sources.py
deltastream_sdk/models/functions.py
deltastream_sdk/models/schema_registries.py
deltastream_sdk/models/schemas.py
deltastream_sdk/models/stores.py
deltastream_sdk/models/streams.py
deltastream_sdk/resources/__init__.py
deltastream_sdk/resources/base.py
deltastream_sdk/resources/changelogs.py
deltastream_sdk/resources/compute_pools.py
deltastream_sdk/resources/databases.py
deltastream_sdk/resources/descriptor_sources.py
deltastream_sdk/resources/entities.py
deltastream_sdk/resources/function_sources.py
deltastream_sdk/resources/functions.py
deltastream_sdk/resources/schema_registries.py
deltastream_sdk/resources/schemas.py
deltastream_sdk/resources/stores.py
deltastream_sdk/resources/streams.py
deltastream_sdk-0.2.1.dist-info/METADATA
deltastream_sdk-0.2.1.dist-info/WHEEL
deltastream_sdk-0.2.1.dist-info/entry_points.txt
deltastream_sdk-0.2.1.dist-info/licenses/LICENSE
deltastream_sdk-0.2.1.dist-info/RECORD
