Metadata-Version: 2.4
Name: deltastream-sdk
Version: 0.2.1
Summary: Python SDK for DeltaStream, built on the DeltaStream Connector library
Project-URL: Homepage, https://github.com/deltastreaminc/deltastream-sdk-python
Project-URL: Issues, https://github.com/deltastreaminc/deltastream-sdk-python/issues
Author-email: "DeltaStream Inc." <support@deltastream.com>
License-Expression: Apache-2.0
License-File: LICENSE
Classifier: Operating System :: OS Independent
Classifier: Programming Language :: Python :: 3
Requires-Python: >=3.11
Requires-Dist: deltastream-connector>=0.3
